Workbook

Sheet 周排班-纵表
A1: 项目类型 | B1: Client Name | C1: Engagement Code | D1: Engagement Name | E1: 订单编号 | F1: WP服务单号 | G1: Staff Name | H1: 周期 | I1: hours
A2: 海信 | B2: Hisense Group Holdings Co., Ltd. | C2: 47115559 | D2: IPO2026-03 Project Voyage_CN | E2: Order47115559- 260729002 | F2: 47115559- EDC260729001 | G2: Marsh.Ma@cn.ey.com | H2: Week15 (2026.10.10) | I2: 2.28
A3: 海信 | B3: Hisense Group Holdings Co., Ltd. | C3: 47115559 | D3: IPO2026-03 Project Voyage_CN | E3: Order47115559- 260729002 | F3: 47115559- EDC260729001 | G3: Rainbow.MG.Xiao@cn.ey.com | H3: Week15 (2026.10.10) | I3: 19.99
A4: 海信 | B4: Hisense Group Holdings Co., Ltd. | C4: 47115559 | D4: IPO2026-03 Project Voyage_CN | E4: Order47115559- 260729002 | F4: 47115559- EDC260729001 | G4: Vivi.W.Yang@cn.ey.com | H4: Week15 (2026.10.10) | I4: 6.28
A5: PE | B5: Shanghai Xinze Sanhe Venture Investment LP | C5: 47127971 | D5: AUD2026-12 Xingze Fund | E5: Order47127971- 260501004 | F5: 47127971- EDC260501001 | G5: Luna.CD.Zhang@cn.ey.com | H5: Week15 (2026.10.10) | I5: 35.56
A6: PE | B6: Shanghai Xinze Sanhe Venture Investment LP | C6: 47127971 | D6: AUD2026-12 Xingze Fund | E6: Order47127971- 260501004 | F6: 47127971- EDC260501001 | G6: Marsh.Ma@cn.ey.com | H6: Week15 (2026.10.10) | I6: 4.06
A7: PE | B7: Shanghai Xinze Sanhe Venture Investment LP | C7: 47127971 | D7: AUD2026-12 Xingze Fund | E7: Order47127971- 260501004 | F7: 47127971- EDC260501001 | G7: Vivi.W.Yang@cn.ey.com | H7: Week15 (2026.10.10) | I7: 11.18
A8: PE | B8: Shanghai Xinze Sanhe Venture Investment LP | C8: 47128472 | D8: AUD2026-12 Xingze Management | E8: Order47128472- 260501003 | F8: 47128472- EDC260501001 | G8: Luna.CD.Zhang@cn.ey.com | H8: Week15 (2026.10.10) | I8: 1.83
A9: PE | B9: Shanghai Xinze Sanhe Venture Investment LP | C9: 47128472 | D9: AUD2026-12 Xingze Management | E9: Order47128472- 260501003 | F9: 47128472- EDC260501001 | G9: Marsh.Ma@cn.ey.com | H9: Week15 (2026.10.10) | I9: 0.21
A10: PE | B10: Shanghai Xinze Sanhe Venture Investment LP | C10: 47128472 | D10: AUD2026-12 Xingze Management | E10: Order47128472- 260501003 | F10: 47128472- EDC260501001 | G10: Vivi.W.Yang@cn.ey.com | H10: Week15 (2026.10.10) | I10: 0.57
A11: PE | B11: Shanghai Lingyi Investment Partnership (limited partnership) | C11: 47128835 | D11: AUD2026-12 01VC USD Fund | E11: Order47128835- 260501004 | F11: 47128835- EDC260501001 | G11: Luna.CD.Zhang@cn.ey.com | H11: Week15 (2026.10.10) | I11: 2.61
A12: PE | B12: Shanghai Lingyi Investment Partnership (limited partnership) | C12: 47128835 | D12: AUD2026-12 01VC USD Fund | E12: Order47128835- 260501004 | F12: 47128835- EDC260501001 | G12: Marsh.Ma@cn.ey.com | H12: Week15 (2026.10.10) | I12: 1.32
A13: PE | B13: Shanghai Lingyi Investment Partnership (limited partnership) | C13: 47128835 | D13: AUD2026-12 01VC USD Fund | E13: Order47128835- 260501004 | F13: 47128835- EDC260501001 | G13: Rainbow.MG.Xiao@cn.ey.com | H13: Week15 (2026.10.10) | I13: 8.93
... A629: PE | B629: Jamesonite Gem (HK) Holdings Limited | C629: 47136348 | D629: AUD2026-12 Warburg Pincus HK SPV JZ | E629: Order47136348- 260504004 | F629: 47136348- EDC260504001 | G629: Luna.CD.Zhang@cn.ey.com | H629: Week45 (2027.05.08) | I629: 23.41

Sheet 周排班-宽表
A1: 项目类型 | B1: Client Name | C1: Engagement Code | D1: Engagement Name | E1: 订单编号 | F1: WP服务单号 | G1: Staff Name | H1: Week15 (2026.10.10) | I1: Week16 (2026.10.17) | J1: Week17 (2026.10.24) | K1: Week18 (2026.10.31) | L1: Week19 (2026.11.07) | M1: Week20 (2026.11.14) | N1: Week21 (2026.11.21) | O1: Week22 (2026.11.28) | P1: Week23 (2026.12.05) | Q1: Week24 (2026.12.12) | R1: Week25 (2026.12.19) | S1: Week26 (2026.12.26) | T1: Week27 (2027.01.02) | U1: Week28 (2027.01.09) | V1: Week29 (2027.01.16) | W1: Week30 (2027.01.23) | X1: Week31 (2027.01.30) | Y1: Week32 (2027.02.06) | Z1: Week33 (2027.02.13) | AA1: Week34 (2027.02.20) | AB1: Week35 (2027.02.27) | AC1: Week36 (2027.03.06) | AD1: Week37 (2027.03.13) | AE1: Week38 (2027.03.20) | AF1: Week39 (2027.03.27) | AG1: Week40 (2027.04.03) | AH1: Week41 (2027.04.10) | AI1: Week42 (2027.04.17) | AJ1: Week43 (2027.04.24) | AK1: Week44 (2027.05.01) | AL1: Week45 (2027.05.08)
A2: HK WAM | B2: Taikang Asset Management (Hong Kong) Company Limited | C2: 47129130 | D2: AUD2026-12 Taikang HK Comps | E2: Order47129130- 260814001 | F2: 47129130- EDC260814001 | G2: Luna.CD.Zhang@cn.ey.com | H2: =SUMIFS('周排班-纵表'!$I:$I,'周排班-纵表'!$C:$C,$C2,'周排班-纵表'!$G:$G,$G2,'周排班-纵表'!$H:$H,H$1) | I2: =SUMIFS('周排班-纵表'!$I:$I,'周排班-纵表'!$C:$C,$C2,'周排班-纵表'!$G:$G,$G2,'周排班-纵表'!$H:$H,I$1) | J2: =SUMIFS('周排班-纵表'!$I:$I,'周排班-纵表'!$C:$C,$C2,'周排班-纵表'!$G:$G,$G2,'周排班-纵表'!$H:$H,J$1) | K2: =SUMIFS('周排班-纵表'!$I:$I,'周排班-纵表'!$C:$C,$C2,'周排班-纵表'!$G:$G,$G2,'周排班-纵表'!$H:$H,K$1) | L2: =SUMIFS('周排班-纵表'!$I:$I,'周排班-纵表'!$C:$C,$C2,'周排班-纵表'!$G:$G,$G2,'周排班-纵表'!$H:$H,L$1) | M2: =SUMIFS('周排班-纵表'!$I:$I,'周排班-纵表'!$C:$C,$C2,'周排班-纵表'!$G:$G,$G2,'周排班-纵表'!$H:$H,M$1) | N2: =SUMIFS('周排班-纵表'!$I:$I,'周排班-纵表'!$C:$C,$C2,'周排班-纵表'!$G:$G,$G2,'周排班-纵表'!$H:$H,N$1) | O2: =SUMIFS('周排班-纵表'!$I:$I,'周排班-纵表'!$C:$C,$C2,'周排班-纵表'!$G:$G,$G2,'周排班-纵表'!$H:$H,O$1) | ... AL2: =SUMIFS('周排班-纵表'!$I:$I,'周排班-纵表'!$C:$C,$C2,'周排班-纵表'!$G:$G,$G2,'周排班-纵表'!$H:$H,AL$1)
A3: HK WAM | B3: Taikang Asset Management (Hong Kong) Company Limited | C3: 47129130 | D3: AUD2026-12 Taikang HK Comps | E3: Order47129130- 260814001 | F3: 47129130- EDC260814001 | G3: Marsh.Ma@cn.ey.com | H3: =SUMIFS('周排班-纵表'!$I:$I,'周排班-纵表'!$C:$C,$C3,'周排班-纵表'!$G:$G,$G3,'周排班-纵表'!$H:$H,H$1) | I3: =SUMIFS('周排班-纵表'!$I:$I,'周排班-纵表'!$C:$C,$C3,'周排班-纵表'!$G:$G,$G3,'周排班-纵表'!$H:$H,I$1) | J3: =SUMIFS('周排班-纵表'!$I:$I,'周排班-纵表'!$C:$C,$C3,'周排班-纵表'!$G:$G,$G3,'周排班-纵表'!$H:$H,J$1) | K3: =SUMIFS('周排班-纵表'!$I:$I,'周排班-纵表'!$C:$C,$C3,'周排班-纵表'!$G:$G,$G3,'周排班-纵表'!$H:$H,K$1) | L3: =SUMIFS('周排班-纵表'!$I:$I,'周排班-纵表'!$C:$C,$C3,'周排班-纵表'!$G:$G,$G3,'周排班-纵表'!$H:$H,L$1) | M3: =SUMIFS('周排班-纵表'!$I:$I,'周排班-纵表'!$C:$C,$C3,'周排班-纵表'!$G:$G,$G3,'周排班-纵表'!$H:$H,M$1) | N3: =SUMIFS('周排班-纵表'!$I:$I,'周排班-纵表'!$C:$C,$C3,'周排班-纵表'!$G:$G,$G3,'周排班-纵表'!$H:$H,N$1) | O3: =SUMIFS('周排班-纵表'!$I:$I,'周排班-纵表'!$C:$C,$C3,'周排班-纵表'!$G:$G,$G3,'周排班-纵表'!$H:$H,O$1) | ... AL3: =SUMIFS('周排班-纵表'!$I:$I,'周排班-纵表'!$C:$C,$C3,'周排班-纵表'!$G:$G,$G3,'周排班-纵表'!$H:$H,AL$1)
A4: HK WAM | B4: Taikang Asset Management (Hong Kong) Company Limited | C4: 47129130 | D4: AUD2026-12 Taikang HK Comps | E4: Order47129130- 260814001 | F4: 47129130- EDC260814001 | G4: Rainbow.MG.Xiao@cn.ey.com | H4: =SUMIFS('周排班-纵表'!$I:$I,'周排班-纵表'!$C:$C,$C4,'周排班-纵表'!$G:$G,$G4,'周排班-纵表'!$H:$H,H$1) | I4: =SUMIFS('周排班-纵表'!$I:$I,'周排班-纵表'!$C:$C,$C4,'周排班-纵表'!$G:$G,$G4,'周排班-纵表'!$H:$H,I$1) | J4: =SUMIFS('周排班-纵表'!$I:$I,'周排班-纵表'!$C:$C,$C4,'周排班-纵表'!$G:$G,$G4,'周排班-纵表'!$H:$H,J$1) | K4: =SUMIFS('周排班-纵表'!$I:$I,'周排班-纵表'!$C:$C,$C4,'周排班-纵表'!$G:$G,$G4,'周排班-纵表'!$H:$H,K$1) | L4: =SUMIFS('周排班-纵表'!$I:$I,'周排班-纵表'!$C:$C,$C4,'周排班-纵表'!$G:$G,$G4,'周排班-纵表'!$H:$H,L$1) | M4: =SUMIFS('周排班-纵表'!$I:$I,'周排班-纵表'!$C:$C,$C4,'周排班-纵表'!$G:$G,$G4,'周排班-纵表'!$H:$H,M$1) | N4: =SUMIFS('周排班-纵表'!$I:$I,'周排班-纵表'!$C:$C,$C4,'周排班-纵表'!$G:$G,$G4,'周排班-纵表'!$H:$H,N$1) | O4: =SUMIFS('周排班-纵表'!$I:$I,'周排班-纵表'!$C:$C,$C4,'周排班-纵表'!$G:$G,$G4,'周排班-纵表'!$H:$H,O$1) | ... AL4: =SUMIFS('周排班-纵表'!$I:$I,'周排班-纵表'!$C:$C,$C4,'周排班-纵表'!$G:$G,$G4,'周排班-纵表'!$H:$H,AL$1)
A5: HK WAM | B5: Taikang Asset Management (Hong Kong) Company Limited | C5: 47129130 | D5: AUD2026-12 Taikang HK Comps | E5: Order47129130- 260814001 | F5: 47129130- EDC260814001 | G5: Vivi.W.Yang@cn.ey.com | H5: =SUMIFS('周排班-纵表'!$I:$I,'周排班-纵表'!$C:$C,$C5,'周排班-纵表'!$G:$G,$G5,'周排班-纵表'!$H:$H,H$1) | I5: =SUMIFS('周排班-纵表'!$I:$I,'周排班-纵表'!$C:$C,$C5,'周排班-纵表'!$G:$G,$G5,'周排班-纵表'!$H:$H,I$1) | J5: =SUMIFS('周排班-纵表'!$I:$I,'周排班-纵表'!$C:$C,$C5,'周排班-纵表'!$G:$G,$G5,'周排班-纵表'!$H:$H,J$1) | K5: =SUMIFS('周排班-纵表'!$I:$I,'周排班-纵表'!$C:$C,$C5,'周排班-纵表'!$G:$G,$G5,'周排班-纵表'!$H:$H,K$1) | L5: =SUMIFS('周排班-纵表'!$I:$I,'周排班-纵表'!$C:$C,$C5,'周排班-纵表'!$G:$G,$G5,'周排班-纵表'!$H:$H,L$1) | M5: =SUMIFS('周排班-纵表'!$I:$I,'周排班-纵表'!$C:$C,$C5,'周排班-纵表'!$G:$G,$G5,'周排班-纵表'!$H:$H,M$1) | N5: =SUMIFS('周排班-纵表'!$I:$I,'周排班-纵表'!$C:$C,$C5,'周排班-纵表'!$G:$G,$G5,'周排班-纵表'!$H:$H,N$1) | O5: =SUMIFS('周排班-纵表'!$I:$I,'周排班-纵表'!$C:$C,$C5,'周排班-纵表'!$G:$G,$G5,'周排班-纵表'!$H:$H,O$1) | ... AL5: =SUMIFS('周排班-纵表'!$I:$I,'周排班-纵表'!$C:$C,$C5,'周排班-纵表'!$G:$G,$G5,'周排班-纵表'!$H:$H,AL$1)
A6: HK WAM | B6: HashKey Capital Limited | C6: 47129402 | D6: AUD2026-12 Hashkey OFC Funds | E6: Order47129402- 260829001 | F6: 47129402- EDC260829001 | G6: Luna.CD.Zhang@cn.ey.com | H6: =SUMIFS('周排班-纵表'!$I:$I,'周排班-纵表'!$C:$C,$C6,'周排班-纵表'!$G:$G,$G6,'周排班-纵表'!$H:$H,H$1) | I6: =SUMIFS('周排班-纵表'!$I:$I,'周排班-纵表'!$C:$C,$C6,'周排班-纵表'!$G:$G,$G6,'周排班-纵表'!$H:$H,I$1) | J6: =SUMIFS('周排班-纵表'!$I:$I,'周排班-纵表'!$C:$C,$C6,'周排班-纵表'!$G:$G,$G6,'周排班-纵表'!$H:$H,J$1) | K6: =SUMIFS('周排班-纵表'!$I:$I,'周排班-纵表'!$C:$C,$C6,'周排班-纵表'!$G:$G,$G6,'周排班-纵表'!$H:$H,K$1) | L6: =SUMIFS('周排班-纵表'!$I:$I,'周排班-纵表'!$C:$C,$C6,'周排班-纵表'!$G:$G,$G6,'周排班-纵表'!$H:$H,L$1) | M6: =SUMIFS('周排班-纵表'!$I:$I,'周排班-纵表'!$C:$C,$C6,'周排班-纵表'!$G:$G,$G6,'周排班-纵表'!$H:$H,M$1) | N6: =SUMIFS('周排班-纵表'!$I:$I,'周排班-纵表'!$C:$C,$C6,'周排班-纵表'!$G:$G,$G6,'周排班-纵表'!$H:$H,N$1) | O6: =SUMIFS('周排班-纵表'!$I:$I,'周排班-纵表'!$C:$C,$C6,'周排班-纵表'!$G:$G,$G6,'周排班-纵表'!$H:$H,O$1) | ... AL6: =SUMIFS('周排班-纵表'!$I:$I,'周排班-纵表'!$C:$C,$C6,'周排班-纵表'!$G:$G,$G6,'周排班-纵表'!$H:$H,AL$1)
A7: HK WAM | B7: HashKey Capital Limited | C7: 47129402 | D7: AUD2026-12 Hashkey OFC Funds | E7: Order47129402- 260829001 | F7: 47129402- EDC260829001 | G7: Marsh.Ma@cn.ey.com | H7: =SUMIFS('周排班-纵表'!$I:$I,'周排班-纵表'!$C:$C,$C7,'周排班-纵表'!$G:$G,$G7,'周排班-纵表'!$H:$H,H$1) | I7: =SUMIFS('周排班-纵表'!$I:$I,'周排班-纵表'!$C:$C,$C7,'周排班-纵表'!$G:$G,$G7,'周排班-纵表'!$H:$H,I$1) | J7: =SUMIFS('周排班-纵表'!$I:$I,'周排班-纵表'!$C:$C,$C7,'周排班-纵表'!$G:$G,$G7,'周排班-纵表'!$H:$H,J$1) | K7: =SUMIFS('周排班-纵表'!$I:$I,'周排班-纵表'!$C:$C,$C7,'周排班-纵表'!$G:$G,$G7,'周排班-纵表'!$H:$H,K$1) | L7: =SUMIFS('周排班-纵表'!$I:$I,'周排班-纵表'!$C:$C,$C7,'周排班-纵表'!$G:$G,$G7,'周排班-纵表'!$H:$H,L$1) | M7: =SUMIFS('周排班-纵表'!$I:$I,'周排班-纵表'!$C:$C,$C7,'周排班-纵表'!$G:$G,$G7,'周排班-纵表'!$H:$H,M$1) | N7: =SUMIFS('周排班-纵表'!$I:$I,'周排班-纵表'!$C:$C,$C7,'周排班-纵表'!$G:$G,$G7,'周排班-纵表'!$H:$H,N$1) | O7: =SUMIFS('周排班-纵表'!$I:$I,'周排班-纵表'!$C:$C,$C7,'周排班-纵表'!$G:$G,$G7,'周排班-纵表'!$H:$H,O$1) | ... AL7: =SUMIFS('周排班-纵表'!$I:$I,'周排班-纵表'!$C:$C,$C7,'周排班-纵表'!$G:$G,$G7,'周排班-纵表'!$H:$H,AL$1)
A8: HK WAM | B8: HashKey Capital Limited | C8: 47129402 | D8: AUD2026-12 Hashkey OFC Funds | E8: Order47129402- 260829001 | F8: 47129402- EDC260829001 | G8: Rainbow.MG.Xiao@cn.ey.com | H8: =SUMIFS('周排班-纵表'!$I:$I,'周排班-纵表'!$C:$C,$C8,'周排班-纵表'!$G:$G,$G8,'周排班-纵表'!$H:$H,H$1) | I8: =SUMIFS('周排班-纵表'!$I:$I,'周排班-纵表'!$C:$C,$C8,'周排班-纵表'!$G:$G,$G8,'周排班-纵表'!$H:$H,I$1) | J8: =SUMIFS('周排班-纵表'!$I:$I,'周排班-纵表'!$C:$C,$C8,'周排班-纵表'!$G:$G,$G8,'周排班-纵表'!$H:$H,J$1) | K8: =SUMIFS('周排班-纵表'!$I:$I,'周排班-纵表'!$C:$C,$C8,'周排班-纵表'!$G:$G,$G8,'周排班-纵表'!$H:$H,K$1) | L8: =SUMIFS('周排班-纵表'!$I:$I,'周排班-纵表'!$C:$C,$C8,'周排班-纵表'!$G:$G,$G8,'周排班-纵表'!$H:$H,L$1) | M8: =SUMIFS('周排班-纵表'!$I:$I,'周排班-纵表'!$C:$C,$C8,'周排班-纵表'!$G:$G,$G8,'周排班-纵表'!$H:$H,M$1) | N8: =SUMIFS('周排班-纵表'!$I:$I,'周排班-纵表'!$C:$C,$C8,'周排班-纵表'!$G:$G,$G8,'周排班-纵表'!$H:$H,N$1) | O8: =SUMIFS('周排班-纵表'!$I:$I,'周排班-纵表'!$C:$C,$C8,'周排班-纵表'!$G:$G,$G8,'周排班-纵表'!$H:$H,O$1) | ... AL8: =SUMIFS('周排班-纵表'!$I:$I,'周排班-纵表'!$C:$C,$C8,'周排班-纵表'!$G:$G,$G8,'周排班-纵表'!$H:$H,AL$1)
A9: HK WAM | B9: HashKey Capital Limited | C9: 47129402 | D9: AUD2026-12 Hashkey OFC Funds | E9: Order47129402- 260829001 | F9: 47129402- EDC260829001 | G9: Vivi.W.Yang@cn.ey.com | H9: =SUMIFS('周排班-纵表'!$I:$I,'周排班-纵表'!$C:$C,$C9,'周排班-纵表'!$G:$G,$G9,'周排班-纵表'!$H:$H,H$1) | I9: =SUMIFS('周排班-纵表'!$I:$I,'周排班-纵表'!$C:$C,$C9,'周排班-纵表'!$G:$G,$G9,'周排班-纵表'!$H:$H,I$1) | J9: =SUMIFS('周排班-纵表'!$I:$I,'周排班-纵表'!$C:$C,$C9,'周排班-纵表'!$G:$G,$G9,'周排班-纵表'!$H:$H,J$1) | K9: =SUMIFS('周排班-纵表'!$I:$I,'周排班-纵表'!$C:$C,$C9,'周排班-纵表'!$G:$G,$G9,'周排班-纵表'!$H:$H,K$1) | L9: =SUMIFS('周排班-纵表'!$I:$I,'周排班-纵表'!$C:$C,$C9,'周排班-纵表'!$G:$G,$G9,'周排班-纵表'!$H:$H,L$1) | M9: =SUMIFS('周排班-纵表'!$I:$I,'周排班-纵表'!$C:$C,$C9,'周排班-纵表'!$G:$G,$G9,'周排班-纵表'!$H:$H,M$1) | N9: =SUMIFS('周排班-纵表'!$I:$I,'周排班-纵表'!$C:$C,$C9,'周排班-纵表'!$G:$G,$G9,'周排班-纵表'!$H:$H,N$1) | O9: =SUMIFS('周排班-纵表'!$I:$I,'周排班-纵表'!$C:$C,$C9,'周排班-纵表'!$G:$G,$G9,'周排班-纵表'!$H:$H,O$1) | ... AL9: =SUMIFS('周排班-纵表'!$I:$I,'周排班-纵表'!$C:$C,$C9,'周排班-纵表'!$G:$G,$G9,'周排班-纵表'!$H:$H,AL$1)
A10: HK WAM | B10: Ortus Capital Management Limited | C10: 47129432 | D10: AUD2026-12 OCML HK | E10: Order47129432- 260812001 | F10: 47129432- EDC260812001 | G10: Luna.CD.Zhang@cn.ey.com | H10: =SUMIFS('周排班-纵表'!$I:$I,'周排班-纵表'!$C:$C,$C10,'周排班-纵表'!$G:$G,$G10,'周排班-纵表'!$H:$H,H$1) | I10: =SUMIFS('周排班-纵表'!$I:$I,'周排班-纵表'!$C:$C,$C10,'周排班-纵表'!$G:$G,$G10,'周排班-纵表'!$H:$H,I$1) | J10: =SUMIFS('周排班-纵表'!$I:$I,'周排班-纵表'!$C:$C,$C10,'周排班-纵表'!$G:$G,$G10,'周排班-纵表'!$H:$H,J$1) | K10: =SUMIFS('周排班-纵表'!$I:$I,'周排班-纵表'!$C:$C,$C10,'周排班-纵表'!$G:$G,$G10,'周排班-纵表'!$H:$H,K$1) | L10: =SUMIFS('周排班-纵表'!$I:$I,'周排班-纵表'!$C:$C,$C10,'周排班-纵表'!$G:$G,$G10,'周排班-纵表'!$H:$H,L$1) | M10: =SUMIFS('周排班-纵表'!$I:$I,'周排班-纵表'!$C:$C,$C10,'周排班-纵表'!$G:$G,$G10,'周排班-纵表'!$H:$H,M$1) | N10: =SUMIFS('周排班-纵表'!$I:$I,'周排班-纵表'!$C:$C,$C10,'周排班-纵表'!$G:$G,$G10,'周排班-纵表'!$H:$H,N$1) | O10: =SUMIFS('周排班-纵表'!$I:$I,'周排班-纵表'!$C:$C,$C10,'周排班-纵表'!$G:$G,$G10,'周排班-纵表'!$H:$H,O$1) | ... AL10: =SUMIFS('周排班-纵表'!$I:$I,'周排班-纵表'!$C:$C,$C10,'周排班-纵表'!$G:$G,$G10,'周排班-纵表'!$H:$H,AL$1)
A11: HK WAM | B11: Ortus Capital Management Limited | C11: 47129432 | D11: AUD2026-12 OCML HK | E11: Order47129432- 260812001 | F11: 47129432- EDC260812001 | G11: Marsh.Ma@cn.ey.com | H11: =SUMIFS('周排班-纵表'!$I:$I,'周排班-纵表'!$C:$C,$C11,'周排班-纵表'!$G:$G,$G11,'周排班-纵表'!$H:$H,H$1) | I11: =SUMIFS('周排班-纵表'!$I:$I,'周排班-纵表'!$C:$C,$C11,'周排班-纵表'!$G:$G,$G11,'周排班-纵表'!$H:$H,I$1) | J11: =SUMIFS('周排班-纵表'!$I:$I,'周排班-纵表'!$C:$C,$C11,'周排班-纵表'!$G:$G,$G11,'周排班-纵表'!$H:$H,J$1) | K11: =SUMIFS('周排班-纵表'!$I:$I,'周排班-纵表'!$C:$C,$C11,'周排班-纵表'!$G:$G,$G11,'周排班-纵表'!$H:$H,K$1) | L11: =SUMIFS('周排班-纵表'!$I:$I,'周排班-纵表'!$C:$C,$C11,'周排班-纵表'!$G:$G,$G11,'周排班-纵表'!$H:$H,L$1) | M11: =SUMIFS('周排班-纵表'!$I:$I,'周排班-纵表'!$C:$C,$C11,'周排班-纵表'!$G:$G,$G11,'周排班-纵表'!$H:$H,M$1) | N11: =SUMIFS('周排班-纵表'!$I:$I,'周排班-纵表'!$C:$C,$C11,'周排班-纵表'!$G:$G,$G11,'周排班-纵表'!$H:$H,N$1) | O11: =SUMIFS('周排班-纵表'!$I:$I,'周排班-纵表'!$C:$C,$C11,'周排班-纵表'!$G:$G,$G11,'周排班-纵表'!$H:$H,O$1) | ... AL11: =SUMIFS('周排班-纵表'!$I:$I,'周排班-纵表'!$C:$C,$C11,'周排班-纵表'!$G:$G,$G11,'周排班-纵表'!$H:$H,AL$1)
A12: HK WAM | B12: Ortus Capital Management Limited | C12: 47129432 | D12: AUD2026-12 OCML HK | E12: Order47129432- 260812001 | F12: 47129432- EDC260812001 | G12: Rainbow.MG.Xiao@cn.ey.com | H12: =SUMIFS('周排班-纵表'!$I:$I,'周排班-纵表'!$C:$C,$C12,'周排班-纵表'!$G:$G,$G12,'周排班-纵表'!$H:$H,H$1) | I12: =SUMIFS('周排班-纵表'!$I:$I,'周排班-纵表'!$C:$C,$C12,'周排班-纵表'!$G:$G,$G12,'周排班-纵表'!$H:$H,I$1) | J12: =SUMIFS('周排班-纵表'!$I:$I,'周排班-纵表'!$C:$C,$C12,'周排班-纵表'!$G:$G,$G12,'周排班-纵表'!$H:$H,J$1) | K12: =SUMIFS('周排班-纵表'!$I:$I,'周排班-纵表'!$C:$C,$C12,'周排班-纵表'!$G:$G,$G12,'周排班-纵表'!$H:$H,K$1) | L12: =SUMIFS('周排班-纵表'!$I:$I,'周排班-纵表'!$C:$C,$C12,'周排班-纵表'!$G:$G,$G12,'周排班-纵表'!$H:$H,L$1) | M12: =SUMIFS('周排班-纵表'!$I:$I,'周排班-纵表'!$C:$C,$C12,'周排班-纵表'!$G:$G,$G12,'周排班-纵表'!$H:$H,M$1) | N12: =SUMIFS('周排班-纵表'!$I:$I,'周排班-纵表'!$C:$C,$C12,'周排班-纵表'!$G:$G,$G12,'周排班-纵表'!$H:$H,N$1) | O12: =SUMIFS('周排班-纵表'!$I:$I,'周排班-纵表'!$C:$C,$C12,'周排班-纵表'!$G:$G,$G12,'周排班-纵表'!$H:$H,O$1) | ... AL12: =SUMIFS('周排班-纵表'!$I:$I,'周排班-纵表'!$C:$C,$C12,'周排班-纵表'!$G:$G,$G12,'周排班-纵表'!$H:$H,AL$1)
A13: HK WAM | B13: Ortus Capital Management Limited | C13: 47129432 | D13: AUD2026-12 OCML HK | E13: Order47129432- 260812001 | F13: 47129432- EDC260812001 | G13: Vivi.W.Yang@cn.ey.com | H13: =SUMIFS('周排班-纵表'!$I:$I,'周排班-纵表'!$C:$C,$C13,'周排班-纵表'!$G:$G,$G13,'周排班-纵表'!$H:$H,H$1) | I13: =SUMIFS('周排班-纵表'!$I:$I,'周排班-纵表'!$C:$C,$C13,'周排班-纵表'!$G:$G,$G13,'周排班-纵表'!$H:$H,I$1) | J13: =SUMIFS('周排班-纵表'!$I:$I,'周排班-纵表'!$C:$C,$C13,'周排班-纵表'!$G:$G,$G13,'周排班-纵表'!$H:$H,J$1) | K13: =SUMIFS('周排班-纵表'!$I:$I,'周排班-纵表'!$C:$C,$C13,'周排班-纵表'!$G:$G,$G13,'周排班-纵表'!$H:$H,K$1) | L13: =SUMIFS('周排班-纵表'!$I:$I,'周排班-纵表'!$C:$C,$C13,'周排班-纵表'!$G:$G,$G13,'周排班-纵表'!$H:$H,L$1) | M13: =SUMIFS('周排班-纵表'!$I:$I,'周排班-纵表'!$C:$C,$C13,'周排班-纵表'!$G:$G,$G13,'周排班-纵表'!$H:$H,M$1) | N13: =SUMIFS('周排班-纵表'!$I:$I,'周排班-纵表'!$C:$C,$C13,'周排班-纵表'!$G:$G,$G13,'周排班-纵表'!$H:$H,N$1) | O13: =SUMIFS('周排班-纵表'!$I:$I,'周排班-纵表'!$C:$C,$C13,'周排班-纵表'!$G:$G,$G13,'周排班-纵表'!$H:$H,O$1) | ... AL13: =SUMIFS('周排班-纵表'!$I:$I,'周排班-纵表'!$C:$C,$C13,'周排班-纵表'!$G:$G,$G13,'周排班-纵表'!$H:$H,AL$1)
... A107: 海信 | B107: Hisense Group Holdings Co., Ltd. | C107: 47115559 | D107: IPO2026-03 Project Voyage_CN | E107: Order47115559- 260729002 | F107: 47115559- EDC260729001 | G107: Vivi.W.Yang@cn.ey.com | H107: =SUMIFS('周排班-纵表'!$I:$I,'周排班-纵表'!$C:$C,$C107,'周排班-纵表'!$G:$G,$G107,'周排班-纵表'!$H:$H,H$1) | I107: =SUMIFS('周排班-纵表'!$I:$I,'周排班-纵表'!$C:$C,$C107,'周排班-纵表'!$G:$G,$G107,'周排班-纵表'!$H:$H,I$1) | J107: =SUMIFS('周排班-纵表'!$I:$I,'周排班-纵表'!$C:$C,$C107,'周排班-纵表'!$G:$G,$G107,'周排班-纵表'!$H:$H,J$1) | K107: =SUMIFS('周排班-纵表'!$I:$I,'周排班-纵表'!$C:$C,$C107,'周排班-纵表'!$G:$G,$G107,'周排班-纵表'!$H:$H,K$1) | L107: =SUMIFS('周排班-纵表'!$I:$I,'周排班-纵表'!$C:$C,$C107,'周排班-纵表'!$G:$G,$G107,'周排班-纵表'!$H:$H,L$1) | M107: =SUMIFS('周排班-纵表'!$I:$I,'周排班-纵表'!$C:$C,$C107,'周排班-纵表'!$G:$G,$G107,'周排班-纵表'!$H:$H,M$1) | N107: =SUMIFS('周排班-纵表'!$I:$I,'周排班-纵表'!$C:$C,$C107,'周排班-纵表'!$G:$G,$G107,'周排班-纵表'!$H:$H,N$1) | O107: =SUMIFS('周排班-纵表'!$I:$I,'周排班-纵表'!$C:$C,$C107,'周排班-纵表'!$G:$G,$G107,'周排班-纵表'!$H:$H,O$1) | ... AL107: =SUMIFS('周排班-纵表'!$I:$I,'周排班-纵表'!$C:$C,$C107,'周排班-纵表'!$G:$G,$G107,'周排班-纵表'!$H:$H,AL$1)

Sheet 周校验
A1: Staff Name | B1: 周期 | C1: 该周合计 hours | D1: 是否忙季 | E1: 周标准工时 | F1: UT比例 | G1: 是否超硬上限
A2: Luna.CD.Zhang@cn.ey.com | B2: Week15 (2026.10.10) | C2: =SUMIFS('周排班-纵表'!$I:$I,'周排班-纵表'!$G:$G,$A2,'周排班-纵表'!$H:$H,$B2) | D2: =IF(OR(MID($B2,FIND("(",$B2)+6,2)="01",MID($B2,FIND("(",$B2)+6,2)="02",MID($B2,FIND("(",$B2)+6,2)="03"),"是","否") | E2: =IF(IFERROR(VLOOKUP($A2,'人员清单'!$A:$B,2,FALSE),"")="intern",40,IF($D2="是",60,40)) | F2: =ROUND($C2/40,4) | G2: =IF(IFERROR(VLOOKUP($A2,'人员清单'!$A:$B,2,FALSE),"")="intern",IF($C2>40,"是","否"),IF($D2="是",IF($C2>78,"是","否"),IF($C2>48,"是","否")))
A3: Marsh.Ma@cn.ey.com | B3: Week15 (2026.10.10) | C3: =SUMIFS('周排班-纵表'!$I:$I,'周排班-纵表'!$G:$G,$A3,'周排班-纵表'!$H:$H,$B3) | D3: =IF(OR(MID($B3,FIND("(",$B3)+6,2)="01",MID($B3,FIND("(",$B3)+6,2)="02",MID($B3,FIND("(",$B3)+6,2)="03"),"是","否") | E3: =IF(IFERROR(VLOOKUP($A3,'人员清单'!$A:$B,2,FALSE),"")="intern",40,IF($D3="是",60,40)) | F3: =ROUND($C3/40,4) | G3: =IF(IFERROR(VLOOKUP($A3,'人员清单'!$A:$B,2,FALSE),"")="intern",IF($C3>40,"是","否"),IF($D3="是",IF($C3>78,"是","否"),IF($C3>48,"是","否")))
A4: Rainbow.MG.Xiao@cn.ey.com | B4: Week15 (2026.10.10) | C4: =SUMIFS('周排班-纵表'!$I:$I,'周排班-纵表'!$G:$G,$A4,'周排班-纵表'!$H:$H,$B4) | D4: =IF(OR(MID($B4,FIND("(",$B4)+6,2)="01",MID($B4,FIND("(",$B4)+6,2)="02",MID($B4,FIND("(",$B4)+6,2)="03"),"是","否") | E4: =IF(IFERROR(VLOOKUP($A4,'人员清单'!$A:$B,2,FALSE),"")="intern",40,IF($D4="是",60,40)) | F4: =ROUND($C4/40,4) | G4: =IF(IFERROR(VLOOKUP($A4,'人员清单'!$A:$B,2,FALSE),"")="intern",IF($C4>40,"是","否"),IF($D4="是",IF($C4>78,"是","否"),IF($C4>48,"是","否")))
A5: Vivi.W.Yang@cn.ey.com | B5: Week15 (2026.10.10) | C5: =SUMIFS('周排班-纵表'!$I:$I,'周排班-纵表'!$G:$G,$A5,'周排班-纵表'!$H:$H,$B5) | D5: =IF(OR(MID($B5,FIND("(",$B5)+6,2)="01",MID($B5,FIND("(",$B5)+6,2)="02",MID($B5,FIND("(",$B5)+6,2)="03"),"是","否") | E5: =IF(IFERROR(VLOOKUP($A5,'人员清单'!$A:$B,2,FALSE),"")="intern",40,IF($D5="是",60,40)) | F5: =ROUND($C5/40,4) | G5: =IF(IFERROR(VLOOKUP($A5,'人员清单'!$A:$B,2,FALSE),"")="intern",IF($C5>40,"是","否"),IF($D5="是",IF($C5>78,"是","否"),IF($C5>48,"是","否")))
A6: Yuan.Yuan.YY.Chen@cn.ey.com | B6: Week15 (2026.10.10) | C6: =SUMIFS('周排班-纵表'!$I:$I,'周排班-纵表'!$G:$G,$A6,'周排班-纵表'!$H:$H,$B6) | D6: =IF(OR(MID($B6,FIND("(",$B6)+6,2)="01",MID($B6,FIND("(",$B6)+6,2)="02",MID($B6,FIND("(",$B6)+6,2)="03"),"是","否") | E6: =IF(IFERROR(VLOOKUP($A6,'人员清单'!$A:$B,2,FALSE),"")="intern",40,IF($D6="是",60,40)) | F6: =ROUND($C6/40,4) | G6: =IF(IFERROR(VLOOKUP($A6,'人员清单'!$A:$B,2,FALSE),"")="intern",IF($C6>40,"是","否"),IF($D6="是",IF($C6>78,"是","否"),IF($C6>48,"是","否")))
A7: Luna.CD.Zhang@cn.ey.com | B7: Week16 (2026.10.17) | C7: =SUMIFS('周排班-纵表'!$I:$I,'周排班-纵表'!$G:$G,$A7,'周排班-纵表'!$H:$H,$B7) | D7: =IF(OR(MID($B7,FIND("(",$B7)+6,2)="01",MID($B7,FIND("(",$B7)+6,2)="02",MID($B7,FIND("(",$B7)+6,2)="03"),"是","否") | E7: =IF(IFERROR(VLOOKUP($A7,'人员清单'!$A:$B,2,FALSE),"")="intern",40,IF($D7="是",60,40)) | F7: =ROUND($C7/40,4) | G7: =IF(IFERROR(VLOOKUP($A7,'人员清单'!$A:$B,2,FALSE),"")="intern",IF($C7>40,"是","否"),IF($D7="是",IF($C7>78,"是","否"),IF($C7>48,"是","否")))
A8: Marsh.Ma@cn.ey.com | B8: Week16 (2026.10.17) | C8: =SUMIFS('周排班-纵表'!$I:$I,'周排班-纵表'!$G:$G,$A8,'周排班-纵表'!$H:$H,$B8) | D8: =IF(OR(MID($B8,FIND("(",$B8)+6,2)="01",MID($B8,FIND("(",$B8)+6,2)="02",MID($B8,FIND("(",$B8)+6,2)="03"),"是","否") | E8: =IF(IFERROR(VLOOKUP($A8,'人员清单'!$A:$B,2,FALSE),"")="intern",40,IF($D8="是",60,40)) | F8: =ROUND($C8/40,4) | G8: =IF(IFERROR(VLOOKUP($A8,'人员清单'!$A:$B,2,FALSE),"")="intern",IF($C8>40,"是","否"),IF($D8="是",IF($C8>78,"是","否"),IF($C8>48,"是","否")))
A9: Rainbow.MG.Xiao@cn.ey.com | B9: Week16 (2026.10.17) | C9: =SUMIFS('周排班-纵表'!$I:$I,'周排班-纵表'!$G:$G,$A9,'周排班-纵表'!$H:$H,$B9) | D9: =IF(OR(MID($B9,FIND("(",$B9)+6,2)="01",MID($B9,FIND("(",$B9)+6,2)="02",MID($B9,FIND("(",$B9)+6,2)="03"),"是","否") | E9: =IF(IFERROR(VLOOKUP($A9,'人员清单'!$A:$B,2,FALSE),"")="intern",40,IF($D9="是",60,40)) | F9: =ROUND($C9/40,4) | G9: =IF(IFERROR(VLOOKUP($A9,'人员清单'!$A:$B,2,FALSE),"")="intern",IF($C9>40,"是","否"),IF($D9="是",IF($C9>78,"是","否"),IF($C9>48,"是","否")))
A10: Vivi.W.Yang@cn.ey.com | B10: Week16 (2026.10.17) | C10: =SUMIFS('周排班-纵表'!$I:$I,'周排班-纵表'!$G:$G,$A10,'周排班-纵表'!$H:$H,$B10) | D10: =IF(OR(MID($B10,FIND("(",$B10)+6,2)="01",MID($B10,FIND("(",$B10)+6,2)="02",MID($B10,FIND("(",$B10)+6,2)="03"),"是","否") | E10: =IF(IFERROR(VLOOKUP($A10,'人员清单'!$A:$B,2,FALSE),"")="intern",40,IF($D10="是",60,40)) | F10: =ROUND($C10/40,4) | G10: =IF(IFERROR(VLOOKUP($A10,'人员清单'!$A:$B,2,FALSE),"")="intern",IF($C10>40,"是","否"),IF($D10="是",IF($C10>78,"是","否"),IF($C10>48,"是","否")))
A11: Yuan.Yuan.YY.Chen@cn.ey.com | B11: Week16 (2026.10.17) | C11: =SUMIFS('周排班-纵表'!$I:$I,'周排班-纵表'!$G:$G,$A11,'周排班-纵表'!$H:$H,$B11) | D11: =IF(OR(MID($B11,FIND("(",$B11)+6,2)="01",MID($B11,FIND("(",$B11)+6,2)="02",MID($B11,FIND("(",$B11)+6,2)="03"),"是","否") | E11: =IF(IFERROR(VLOOKUP($A11,'人员清单'!$A:$B,2,FALSE),"")="intern",40,IF($D11="是",60,40)) | F11: =ROUND($C11/40,4) | G11: =IF(IFERROR(VLOOKUP($A11,'人员清单'!$A:$B,2,FALSE),"")="intern",IF($C11>40,"是","否"),IF($D11="是",IF($C11>78,"是","否"),IF($C11>48,"是","否")))
A12: Luna.CD.Zhang@cn.ey.com | B12: Week17 (2026.10.24) | C12: =SUMIFS('周排班-纵表'!$I:$I,'周排班-纵表'!$G:$G,$A12,'周排班-纵表'!$H:$H,$B12) | D12: =IF(OR(MID($B12,FIND("(",$B12)+6,2)="01",MID($B12,FIND("(",$B12)+6,2)="02",MID($B12,FIND("(",$B12)+6,2)="03"),"是","否") | E12: =IF(IFERROR(VLOOKUP($A12,'人员清单'!$A:$B,2,FALSE),"")="intern",40,IF($D12="是",60,40)) | F12: =ROUND($C12/40,4) | G12: =IF(IFERROR(VLOOKUP($A12,'人员清单'!$A:$B,2,FALSE),"")="intern",IF($C12>40,"是","否"),IF($D12="是",IF($C12>78,"是","否"),IF($C12>48,"是","否")))
A13: Marsh.Ma@cn.ey.com | B13: Week17 (2026.10.24) | C13: =SUMIFS('周排班-纵表'!$I:$I,'周排班-纵表'!$G:$G,$A13,'周排班-纵表'!$H:$H,$B13) | D13: =IF(OR(MID($B13,FIND("(",$B13)+6,2)="01",MID($B13,FIND("(",$B13)+6,2)="02",MID($B13,FIND("(",$B13)+6,2)="03"),"是","否") | E13: =IF(IFERROR(VLOOKUP($A13,'人员清单'!$A:$B,2,FALSE),"")="intern",40,IF($D13="是",60,40)) | F13: =ROUND($C13/40,4) | G13: =IF(IFERROR(VLOOKUP($A13,'人员清单'!$A:$B,2,FALSE),"")="intern",IF($C13>40,"是","否"),IF($D13="是",IF($C13>78,"是","否"),IF($C13>48,"是","否")))
... A153: Luna.CD.Zhang@cn.ey.com | B153: Week45 (2027.05.08) | C153: =SUMIFS('周排班-纵表'!$I:$I,'周排班-纵表'!$G:$G,$A153,'周排班-纵表'!$H:$H,$B153) | D153: =IF(OR(MID($B153,FIND("(",$B153)+6,2)="01",MID($B153,FIND("(",$B153)+6,2)="02",MID($B153,FIND("(",$B153)+6,2)="03"),"是","否") | E153: =IF(IFERROR(VLOOKUP($A153,'人员清单'!$A:$B,2,FALSE),"")="intern",40,IF($D153="是",60,40)) | F153: =ROUND($C153/40,4) | G153: =IF(IFERROR(VLOOKUP($A153,'人员清单'!$A:$B,2,FALSE),"")="intern",IF($C153>40,"是","否"),IF($D153="是",IF($C153>78,"是","否"),IF($C153>48,"是","否")))

Sheet 项目工时校验
A1: Engagement Code | B1: Engagement Name | C1: 剩余hours | D1: 排班合计 hours | E1: diff | F1: diff 是否 <5h
A2: 47115559 | B2: IPO2026-03 Project Voyage_CN | C2: 361.7 | D2: =SUMIFS('周排班-纵表'!$I:$I,'周排班-纵表'!$C:$C,$A2) | E2: =$D2-$C2 | F2: =IF(ABS($E2)<5,"是","否")
A3: 47127971 | B3: AUD2026-12 Xingze Fund | C3: 169.33 | D3: =SUMIFS('周排班-纵表'!$I:$I,'周排班-纵表'!$C:$C,$A3) | E3: =$D3-$C3 | F3: =IF(ABS($E3)<5,"是","否")
A4: 47128046 | B4: AUD2026-12 FR Funds | C4: 154.87 | D4: =SUMIFS('周排班-纵表'!$I:$I,'周排班-纵表'!$C:$C,$A4) | E4: =$D4-$C4 | F4: =IF(ABS($E4)<5,"是","否")
A5: 47128108 | B5: AUD2026-12 EverYi Capital | C5: 106.49 | D5: =SUMIFS('周排班-纵表'!$I:$I,'周排班-纵表'!$C:$C,$A5) | E5: =$D5-$C5 | F5: =IF(ABS($E5)<5,"是","否")
A6: 47128154 | B6: AUD2026-12 Mirae Asset | C6: 144 | D6: =SUMIFS('周排班-纵表'!$I:$I,'周排班-纵表'!$C:$C,$A6) | E6: =$D6-$C6 | F6: =IF(ABS($E6)<5,"是","否")
A7: 47128202 | B7: AUD2026-12 Hangzhou Huaxin | C7: 491.73 | D7: =SUMIFS('周排班-纵表'!$I:$I,'周排班-纵表'!$C:$C,$A7) | E7: =$D7-$C7 | F7: =IF(ABS($E7)<5,"是","否")
A8: 47128359 | B8: AUD2026-12 Arrace Holding | C8: 26.64 | D8: =SUMIFS('周排班-纵表'!$I:$I,'周排班-纵表'!$C:$C,$A8) | E8: =$D8-$C8 | F8: =IF(ABS($E8)<5,"是","否")
A9: 47128364 | B9: AUD2026-12 Great Wall Funds | C9: 880.53 | D9: =SUMIFS('周排班-纵表'!$I:$I,'周排班-纵表'!$C:$C,$A9) | E9: =$D9-$C9 | F9: =IF(ABS($E9)<5,"是","否")
A10: 47128421 | B10: AUD2026-12 PA Funds | C10: 132.49 | D10: =SUMIFS('周排班-纵表'!$I:$I,'周排班-纵表'!$C:$C,$A10) | E10: =$D10-$C10 | F10: =IF(ABS($E10)<5,"是","否")
A11: 47128469 | B11: AUD2026-12 Warburg Pincus US Fund | C11: 33.74 | D11: =SUMIFS('周排班-纵表'!$I:$I,'周排班-纵表'!$C:$C,$A11) | E11: =$D11-$C11 | F11: =IF(ABS($E11)<5,"是","否")
A12: 47128472 | B12: AUD2026-12 Xingze Management | C12: 15.24 | D12: =SUMIFS('周排班-纵表'!$I:$I,'周排班-纵表'!$C:$C,$A12) | E12: =$D12-$C12 | F12: =IF(ABS($E12)<5,"是","否")
A13: 47128515 | B13: AUD2026-12 OFC Fund | C13: 38.74 | D13: =SUMIFS('周排班-纵表'!$I:$I,'周排班-纵表'!$C:$C,$A13) | E13: =$D13-$C13 | F13: =IF(ABS($E13)<5,"是","否")
... A29: 47136348 | B29: AUD2026-12 Warburg Pincus HK SPV JZ | C29: 308.61 | D29: =SUMIFS('周排班-纵表'!$I:$I,'周排班-纵表'!$C:$C,$A29) | E29: =$D29-$C29 | F29: =IF(ABS($E29)<5,"是","否")

Sheet 项目关键节点
A1: Engagement Code | B1: Engagement Name | C1: 节点类型 | D1: 日期 | E1: 参与人员 | F1: 提醒7天前 | G1: 提醒5天前 | H1: 提醒3天前 | I1: 提醒当天
A2: 47115559 | B2: IPO2026-03 Project Voyage_CN | C2: 预审开始 | D2: 46307 | E2: Marsh.Ma@cn.ey.com、Vivi.W.Yang@cn.ey.com、Luna.CD.Zhang@cn.ey.com、Rainbow.MG.Xiao@cn.ey.com、Yuan.Yuan.YY.Chen@cn.ey.com | F2: =$D2-7 | G2: =$D2-5 | H2: =$D2-3 | I2: =$D2-0
A3: 47128835 | B3: AUD2026-12 01VC USD Fund | C3: 预审开始 | D3: 46307 | E3: Marsh.Ma@cn.ey.com、Vivi.W.Yang@cn.ey.com、Luna.CD.Zhang@cn.ey.com、Rainbow.MG.Xiao@cn.ey.com、Yuan.Yuan.YY.Chen@cn.ey.com | F3: =$D3-7 | G3: =$D3-5 | H3: =$D3-3 | I3: =$D3-0
A4: 47129548 | B4: AUD2026-12 ICBCA | C4: 预审开始 | D4: 46307 | E4: Marsh.Ma@cn.ey.com、Vivi.W.Yang@cn.ey.com、Yuan.Yuan.YY.Chen@cn.ey.com、Luna.CD.Zhang@cn.ey.com、Rainbow.MG.Xiao@cn.ey.com、InternB、InternA | F4: =$D4-7 | G4: =$D4-5 | H4: =$D4-3 | I4: =$D4-0
A5: 47127971 | B5: AUD2026-12 Xingze Fund | C5: 预审开始 | D5: 46308 | E5: Marsh.Ma@cn.ey.com、Vivi.W.Yang@cn.ey.com、Luna.CD.Zhang@cn.ey.com、Rainbow.MG.Xiao@cn.ey.com、Yuan.Yuan.YY.Chen@cn.ey.com | F5: =$D5-7 | G5: =$D5-5 | H5: =$D5-3 | I5: =$D5-0
A6: 47128472 | B6: AUD2026-12 Xingze Management | C6: 预审开始 | D6: 46308 | E6: Marsh.Ma@cn.ey.com、Vivi.W.Yang@cn.ey.com、Luna.CD.Zhang@cn.ey.com | F6: =$D6-7 | G6: =$D6-5 | H6: =$D6-3 | I6: =$D6-0
A7: 47127971 | B7: AUD2026-12 Xingze Fund | C7: 预审交付 | D7: 46311 | E7: Marsh.Ma@cn.ey.com、Vivi.W.Yang@cn.ey.com、Luna.CD.Zhang@cn.ey.com、Rainbow.MG.Xiao@cn.ey.com、Yuan.Yuan.YY.Chen@cn.ey.com | F7: =$D7-7 | G7: =$D7-5 | H7: =$D7-3 | I7: =$D7-0
A8: 47128472 | B8: AUD2026-12 Xingze Management | C8: 预审交付 | D8: 46314 | E8: Marsh.Ma@cn.ey.com、Vivi.W.Yang@cn.ey.com、Luna.CD.Zhang@cn.ey.com | F8: =$D8-7 | G8: =$D8-5 | H8: =$D8-3 | I8: =$D8-0
A9: 47128835 | B9: AUD2026-12 01VC USD Fund | C9: 预审交付 | D9: 46318 | E9: Marsh.Ma@cn.ey.com、Vivi.W.Yang@cn.ey.com、Luna.CD.Zhang@cn.ey.com、Rainbow.MG.Xiao@cn.ey.com、Yuan.Yuan.YY.Chen@cn.ey.com | F9: =$D9-7 | G9: =$D9-5 | H9: =$D9-3 | I9: =$D9-0
A10: 47115559 | B10: IPO2026-03 Project Voyage_CN | C10: 预审交付 | D10: 46325 | E10: Marsh.Ma@cn.ey.com、Vivi.W.Yang@cn.ey.com、Luna.CD.Zhang@cn.ey.com、Rainbow.MG.Xiao@cn.ey.com、Yuan.Yuan.YY.Chen@cn.ey.com | F10: =$D10-7 | G10: =$D10-5 | H10: =$D10-3 | I10: =$D10-0
A11: 47128202 | B11: AUD2026-12 Hangzhou Huaxin | C11: 预审开始 | D11: 46331 | E11: Marsh.Ma@cn.ey.com、Vivi.W.Yang@cn.ey.com、Luna.CD.Zhang@cn.ey.com、Rainbow.MG.Xiao@cn.ey.com、Yuan.Yuan.YY.Chen@cn.ey.com | F11: =$D11-7 | G11: =$D11-5 | H11: =$D11-3 | I11: =$D11-0
A12: 47129548 | B12: AUD2026-12 ICBCA | C12: 预审交付 | D12: 46346 | E12: Marsh.Ma@cn.ey.com、Vivi.W.Yang@cn.ey.com、Yuan.Yuan.YY.Chen@cn.ey.com、Luna.CD.Zhang@cn.ey.com、Rainbow.MG.Xiao@cn.ey.com、InternB、InternA | F12: =$D12-7 | G12: =$D12-5 | H12: =$D12-3 | I12: =$D12-0
A13: 47128359 | B13: AUD2026-12 Arrace Holding | C13: 预审开始 | D13: 46349 | E13: Marsh.Ma@cn.ey.com、Vivi.W.Yang@cn.ey.com、Luna.CD.Zhang@cn.ey.com | F13: =$D13-7 | G13: =$D13-5 | H13: =$D13-3 | I13: =$D13-0
... A79: 47136348 | B79: AUD2026-12 Warburg Pincus HK SPV JZ | C79: 年审交付 | D79: 46512 | E79: Marsh.Ma@cn.ey.com、Vivi.W.Yang@cn.ey.com、Luna.CD.Zhang@cn.ey.com、Rainbow.MG.Xiao@cn.ey.com | F79: =$D79-7 | G79: =$D79-5 | H79: =$D79-3 | I79: =$D79-0

Sheet 日历提醒汇总
A1: 提醒日期 | B1: 提醒阶段 | C1: 涉及节点数 | D1: 汇总标题 | E1: 汇总详情
A2: 46394 | B2: 当天 | C2: 1 | D2: DDL汇总：2027-01-07（1项） | E2: AUD2026-12 01VC USD Fund（47128835）| 年审开始 | 2027-01-07 | 距DDL0天
A3: 46420 | B3: 当天 | C3: 1 | D3: DDL汇总：2027-02-02（1项） | E3: AUD2026-12 Arrace Holding（47128359）| 年审开始 | 2027-02-02 | 距DDL0天
A4: 46466 | B4: 当天 | C4: 2 | D4: DDL汇总：2027-03-20（2项） | E4: AUD2026-12 BOYU CAPITAL FUND（47129715）| 年审交付 | 2027-03-20 | 距DDL0天 AUD2026-12 E Fund IM（47129692）| 年审交付 | 2027-03-20 | 距DDL0天
A5: 46371 | B5: 当天 | C5: 2 | D5: DDL汇总：2026-12-15（2项） | E5: AUD2026-12 CMBILM（47133720）| 预审开始 | 2026-12-15 | 距DDL0天 AUD2026-12 Warburg Pincus US Fund（47128469）| 预审开始 | 2026-12-15 | 距DDL0天
A6: 46467 | B6: 当天 | C6: 1 | D6: DDL汇总：2027-03-21（1项） | E6: AUD2026-12 CMBILM（47133720）| 年审开始 | 2027-03-21 | 距DDL0天
A7: 46478 | B7: 当天 | C7: 6 | D7: DDL汇总：2027-04-01（6项） | E7: AUD2026-12 COS-CAPITAL HK INTL（47129459）| 年审交付 | 2027-04-01 | 距DDL0天 AUD2026-12 DST Investment Mgt（47129679）| 年审交付 | 2027-04-01 | 距DDL0天 AUD2026-12 Hashkey OFC Funds（47129402）| 年审交付 | 2027-04-01 | 距DDL0天 AUD2026-12 OCML HK（47129432）| 年审交付 | 2027-04-01 | 距DDL0天 AUD2026-12 Shinka Capital（47129702）| 年审交付 | 2027-04-01 | 距DDL0天 AUD2026-12 Taikang HK Comps（47129130）| 年审交付 | 2027-04-01 | 距DDL0天
A8: 46447 | B8: 当天 | C8: 5 | D8: DDL汇总：2027-03-01（5项） | E8: AUD2026-12 FR Funds（47128046）| 年审交付 | 2027-03-01 | 距DDL0天 AUD2026-12 Great Wall Funds（47128364）| 年审交付 | 2027-03-01 | 距DDL0天 AUD2026-12 Hashkey OFC Funds（47129402）| 年审开始 | 2027-03-01 | 距DDL0天 AUD2026-12 Invesco GW Funds（47128706）| 年审交付 | 2027-03-01 | 距DDL0天 AUD2026-12 Warburg Pincus US Fund（47128469）| 年审开始 | 2027-03-01 | 距DDL0天
A9: 46477 | B9: 当天 | C9: 2 | D9: DDL汇总：2027-03-31（2项） | E9: AUD2026-12 HSQH Funds（47128633）| 年审交付 | 2027-03-31 | 距DDL0天 AUD2026-12 ICBCA（47129548）| 年审交付 | 2027-03-31 | 距DDL0天
A10: 46331 | B10: 当天 | C10: 1 | D10: DDL汇总：2026-11-05（1项） | E10: AUD2026-12 Hangzhou Huaxin（47128202）| 预审开始 | 2026-11-05 | 距DDL0天
A11: 46361 | B11: 当天 | C11: 1 | D11: DDL汇总：2026-12-05（1项） | E11: AUD2026-12 Hangzhou Huaxin（47128202）| 预审交付 | 2026-12-05 | 距DDL0天
A12: 46446 | B12: 当天 | C12: 1 | D12: DDL汇总：2027-02-28（1项） | E12: AUD2026-12 ICBCM（47129069）| 年审交付 | 2027-02-28 | 距DDL0天
A13: 46357 | B13: 当天 | C13: 1 | D13: DDL汇总：2026-12-01（1项） | E13: AUD2026-12 Mirae Asset（47128154）| 预审开始 | 2026-12-01 | 距DDL0天
... A129: 46308 | B129: 混合 | C129: 3 | D129: DDL汇总：2026-10-13（3项） | E129: AUD2026-12 Xingze Fund（47127971）| 预审交付 | 2026-10-16 | 距DDL3天 AUD2026-12 Xingze Fund（47127971）| 预审开始 | 2026-10-13 | 距DDL0天 AUD2026-12 Xingze Management（47128472）| 预审开始 | 2026-10-13 | 距DDL0天

Sheet 项目基础
A1: Engagement Code | B1: Engagement Name | C1: 项目类型 | D1: 剩余hours
A2: 47115559 | B2: IPO2026-03 Project Voyage_CN | C2: 海信 | D2: 361.7
A3: 47127971 | B3: AUD2026-12 Xingze Fund | C3: PE | D3: 169.33
A4: 47128046 | B4: AUD2026-12 FR Funds | C4: 公募 | D4: 154.87
A5: 47128108 | B5: AUD2026-12 EverYi Capital | C5: PE | D5: 106.49
A6: 47128154 | B6: AUD2026-12 Mirae Asset | C6: PE | D6: 144
A7: 47128202 | B7: AUD2026-12 Hangzhou Huaxin | C7: PE | D7: 491.73
A8: 47128359 | B8: AUD2026-12 Arrace Holding | C8: PE | D8: 26.64
A9: 47128364 | B9: AUD2026-12 Great Wall Funds | C9: 公募 | D9: 880.53
A10: 47128421 | B10: AUD2026-12 PA Funds | C10: 公募 | D10: 132.49
A11: 47128469 | B11: AUD2026-12 Warburg Pincus US Fund | C11: PE | D11: 33.74
A12: 47128472 | B12: AUD2026-12 Xingze Management | C12: PE | D12: 15.24
A13: 47128515 | B13: AUD2026-12 OFC Fund | C13: PE | D13: 38.74
... A29: 47136348 | B29: AUD2026-12 Warburg Pincus HK SPV JZ | C29: PE | D29: 308.61

Sheet 源数据-WP服务单
A1: Client Name | B1: Engagement Code | C1: Engagement Name | D1: 订单编号 | E1: WP 服务单号 | F1: Audit EIC | G1: Audit Report Date | H1: Outlook Hours | I1: 剩余hours | J1: 预审（10-12月）预计hours | K1: 1-3月预计hours | L1: 4-6月预计hours | M1: 项目类型 | N1: 预审开始时间 | O1: 预审交付时间 | P1: 年审开始时间 | Q1: 年审交付时间 | R1: 参与人员1 | S1: 参与人员2 | T1: 参与人员3 | U1: 参与人员4 | V1: 参与人员5 | W1: 参与人员6 | X1: 参与人员7
A2: HashKey Capital Limited | B2: 47129402 | C2: AUD2026-12 Hashkey OFC Funds | D2: Order47129402- 260829001 | E2: 47129402- EDC260829001 | F2: Donald.Yue | G2: 46515 | H2: 60.06 | I2: 60.06 | K2: 54.054 | L2: 6.006 | M2: HK WAM | P2: 46447 | Q2: 46478 | R2: Marsh | S2: Vivi | T2: Luna | U2: Rainbow
A3: Boyu Capital Advisory Co. Limited | B3: 47129715 | C3: AUD2026-12 BOYU CAPITAL FUND | D3: Order47129715- 260814001 | E3: 47129715- EDC260814001 | F3: Michelle.Chung,Donald.Yue | G3: 46472 | H3: 13.81 | I3: 13.81 | K3: 13.81 | M3: HK WAM | P3: 46433 | Q3: 46466 | R3: Marsh | S3: Vivi | T3: Luna | U3: Rainbow
A4: E Fund International Holdings Limited | B4: 47129692 | C4: AUD2026-12 E Fund IM | D4: Order47129692- 260814001 | E4: 47129692- EDC260814001 | F4: Michelle.Chung,Daniel.Kong | G4: 46472 | H4: 5.01 | I4: 5.01 | K4: 5.01 | M4: HK WAM | P4: 46433 | Q4: 46466 | R4: Marsh | S4: Vivi | T4: Luna | U4: Rainbow
A5: SHINKA CAPITAL MANAGEMENT LIMITED | B5: 47129702 | C5: AUD2026-12 Shinka Capital | D5: Order47129702- 260814001 | E5: 47129702- EDC260814001 | F5: Michelle.Chung | G5: 46492 | H5: 17.01 | I5: 17.01 | K5: 17.01 | M5: HK WAM | P5: 46433 | Q5: 46478 | R5: Marsh | S5: Vivi | T5: Luna | U5: Rainbow
A6: DST Investment Management Limited | B6: 47129679 | C6: AUD2026-12 DST Investment Mgt | D6: Order47129679- 260814001 | E6: 47129679- EDC260814001 | F6: Donald.Yue | G6: 46504 | H6: 22.01 | I6: 22.01 | K6: 22.01 | M6: HK WAM | P6: 46433 | Q6: 46478 | R6: Marsh | S6: Vivi | T6: Luna | U6: Rainbow
A7: Taikang Asset Management (Hong Kong) Company Limited | B7: 47129130 | C7: AUD2026-12 Taikang HK Comps | D7: Order47129130- 260814001 | E7: 47129130- EDC260814001 | F7: Donald.Yue | G7: 46528 | H7: 17.01 | I7: 17.01 | K7: 17.01 | M7: HK WAM | P7: 46433 | Q7: 46478 | R7: Marsh | S7: Vivi | T7: Luna | U7: Rainbow
A8: Ortus Capital Management Limited | B8: 47129432 | C8: AUD2026-12 OCML HK | D8: Order47129432- 260812001 | E8: 47129432- EDC260812001 | F8: Daniel.Kong | G8: 46505 | H8: 17.22 | I8: 17.22 | K8: 17.22 | M8: HK WAM | P8: 46433 | Q8: 46478 | R8: Marsh | S8: Vivi | T8: Luna | U8: Rainbow
A9: COS-Capital Hong Kong International Co. Limited | B9: 47129459 | C9: AUD2026-12 COS-CAPITAL HK INTL | D9: Order47129459- 260812001 | E9: 47129459- EDC260812001 | F9: Jason.CF.Tam | G9: 46499 | H9: 18.81 | I9: 18.81 | K9: 18.81 | M9: HK WAM | P9: 46433 | Q9: 46478 | R9: Marsh | S9: Vivi | T9: Luna | U9: Rainbow
A10: Industrial And Commercial Bank of China (Asia) Limited | B10: 47129548 | C10: AUD2026-12 ICBCA | D10: Order47129548- 260501002 | E10: 47129548- EDC260501001 | F10: Gordon Chu | G10: 46507 | H10: 1316.11 | I10: 1316.11 | J10: 394.833 | K10: 921.277 | M10: ICBC | N10: 46307 | O10: 46346 | P10: 46377 | Q10: 46477 | R10: Marsh | S10: Vivi | T10: Yuan | U10: Luna | V10: Rainbow | W10: InternB | X10: InternA
A11: EverYi Capital Asia Fund, L.P. | B11: 47128108 | C11: AUD2026-12 EverYi Capital | D11: Order47128108- 260501005 | E11: 47128108- EDC260504001 | F11: eric-yl.qin | G11: 46501 | H11: 106.49 | I11: 106.49 | J11: 31.947 | K11: 63.894 | L11: 10.649 | M11: PE | P11: 46388 | Q11: 46437 | R11: Marsh | S11: Vivi | T11: Luna | U11: Rainbow | V11: Yuan
A12: Ping An Fund Management Company Limited | B12: 47128421 | C12: AUD2026-12 PA Funds | D12: Order47128421- 260501003 | E12: 47128421- EDC260501001 | F12: Candy-YX.Huang,Hannah.YH.Yu | G12: 46470 | H12: 132.49 | I12: 132.49 | K12: 732.49 | M12: 公募 | P12: 46384 | Q12: 46419 | R12: Marsh | S12: Yuan | T12: Rainbow | U12: InternA | V12: InternB
A13: Vivo (Suzhou) Health Industry Investment Fund Limited Partnership | B13: 47128359 | C13: AUD2026-12 Arrace Holding | D13: Order47128359- 260501004 | E13: 47128359- EDC260501001 | F13: Sherry.LXJ.Liu | G13: 46505 | H13: 26.64 | I13: 26.64 | J13: 7.992 | K13: 18.648 | M13: PE | N13: 46349 | O13: 46352 | P13: 46420 | Q13: 46440 | R13: Marsh | S13: Vivi | T13: Luna
A14: Industrial And Commercial Bank of China (Macau) Limited | B14: 47129069 | C14: AUD2026-12 ICBCM | D14: Order47129069- 260731001 | E14: 47129069- EDC260731001 | F14: Tony MH Chiu | G14: 46476 | H14: 88 | I14: 88 | J14: 26.4 | K14: 61.6 | M14: ICBC | P14: 46377 | Q14: 46446 | R14: Marsh | S14: Vivi | T14: Rainbow | U14: Luna | V14: InternA
A15: Hangzhou Huaxin Yunkai Equity Shares Investment Partnership Enterprise (Limited Partnership) | B15: 47128202 | C15: AUD2026-12 Hangzhou Huaxin | D15: Order47128202- 260501004 | E15: 47128202- EDC260501001 | F15: iris-l.liu,Eric C Chen | G15: 46472 | H15: 491.73 | I15: 491.73 | J15: 147.519 | K15: 319.6245 | L15: 24.5865 | M15: PE | N15: 2026年11月初 | O15: 2026年12月初 | P15: 2027年1月中 | Q15: 2027年2月底 | R15: Marsh | S15: Vivi | T15: Luna | U15: Rainbow | V15: Yuan
A16: Mirae Asset Alternative Investment Management (Shanghai) Co., Ltd. | B16: 47128154 | C16: AUD2026-12 Mirae Asset | D16: Order47128154- 260501004 | E16: 47128154- EDC260504001 | F16: Freya.Huang,Sarah.Q.Liu | G16: 46458 | H16: 144 | I16: 144 | J16: 43.2 | K16: 100.8 | M16: PE | N16: 46357 | O16: 46386 | P16: 46388 | Q16: 46405 | R16: Marsh | S16: Vivi | T16: Luna | U16: Rainbow | V16: Yuan
A17: Hang Seng Qianhai Fund Management Company Limited | B17: 47128633 | C17: AUD2026-12 HSQH Funds | D17: Order47128633- 260501004 | E17: 47128633- EDC260501001 | F17: Hannah.YH.Yu | G17: 46477 | H17: 131.17 | I17: 131.17 | K17: 131.17 | M17: 公募 | P17: 46377 | Q17: 46477 | R17: Marsh | S17: Yuan | T17: Rainbow | U17: InternA | V17: InternB
A18: Invesco Great Wall Fund Management Co.,Ltd. | B18: 47128706 | C18: AUD2026-12 Invesco GW Funds | D18: Order47128706- 260501003 | E18: 47128706- EDC260501001 | F18: Andy-EL.Lin,Candy-YX.Huang | G18: 46471 | H18: 200 | I18: 200 | J18: 277.194 | K18: 646.786 | M18: 公募 | P18: 46377 | Q18: 46447 | R18: Marsh | S18: Yuan | T18: Rainbow | U18: InternA | V18: InternB
A19: Xiamen Fuhai New Materials Phase Iii Venture Capital Partnership Enterprise(Limi ted Partnership) | B19: 47128515 | C19: AUD2026-12 OFC Fund | D19: Order47128515- 260501002 | E19: 47128515- EDC260501001 | F19: Tony.L.Tao,iris-l.liu | G19: 46477 | H19: 38.74 | I19: 38.74 | J19: 11.622 | K19: 27.118 | M19: PE | P19: 46395 | Q19: 46419 | R19: Marsh | S19: Vivi | T19: Luna
A20: Vivo (Suzhou) Health Industry Investment Fund Limited Partnership | B20: 47128684 | C20: AUD2026-12 Vivo Capital | D20: Order47128684- 260501004 | E20: 47128684- EDC260501001 | F20: Sherry.LXJ.Liu | G20: 46458 | H20: 37.47 | I20: 37.47 | J20: 11.241 | K20: 26.229 | M20: PE | N20: 46349 | O20: 46352 | P20: 46388 | Q20: 46440 | R20: Marsh | S20: Vivi | T20: Luna
A21: Shanghai Xinze Sanhe Venture Investment LP | B21: 47127971 | C21: AUD2026-12 Xingze Fund | D21: Order47127971- 260501004 | E21: 47127971- EDC260501001 | F21: Tony.L.Tao | G21: 46446 | H21: 169.33 | I21: 169.33 | J21: 50.799 | K21: 118.531 | M21: PE | N21: 46308 | O21: 46311 | P21: 46393 | Q21: 46402 | R21: Marsh | S21: Vivi | T21: Luna | U21: Rainbow | V21: Yuan
A22: Great Wall Fund Management Co., Ltd | B22: 47128364 | C22: AUD2026-12 Great Wall Funds | D22: Order47128364- 260501004 | E22: 47128364- EDC260501001 | F22: Candy-YX.Huang,Hannah.YH.Yu | G22: 46472 | H22: 880.53 | I22: 880.53 | J22: 269.259 | K22: 628.271 | M22: 公募 | P22: 46377 | Q22: 46447 | R22: Marsh | S22: Yuan | T22: Rainbow | U22: InternA | V22: InternB
A23: Shanghai Xinze Sanhe Venture Investment LP | B23: 47128472 | C23: AUD2026-12 Xingze Management | D23: Order47128472- 260501003 | E23: 47128472- EDC260501001 | F23: Tony.L.Tao | G23: 46500 | H23: 15.24 | I23: 15.24 | J23: 4.572 | K23: 10.668 | M23: PE | N23: 46308 | O23: 46314 | P23: 46393 | Q23: 46407 | R23: Marsh | S23: Vivi | T23: Luna
A24: WP Financial Investment, LP | B24: 47128469 | C24: AUD2026-12 Warburg Pincus US Fund | D24: Order47128469- 260501002 | E24: 47128469- EDC260501001 | F24: Eric C Chen | G24: 46492 | H24: 33.74 | I24: 33.74 | J24: 10.122 | K24: 23.618 | M24: PE | N24: 46371 | O24: 46379 | P24: 46447 | Q24: 46456 | R24: Marsh | S24: Vivi | T24: Luna
A25: Shanghai Lingyi Investment Partnership (limited partnership) | B25: 47128835 | C25: AUD2026-12 01VC USD Fund | D25: Order47128835- 260501004 | E25: 47128835- EDC260501001 | F25: shirley-y.chen,Eric C Chen | G25: 46471 | H25: 131.87 | I25: 131.87 | J25: 39.561 | K25: 92.309 | M25: PE | N25: 46307 | O25: 46318 | P25: 46394 | Q25: 46400 | R25: Marsh | S25: Vivi | T25: Luna | U25: Rainbow | V25: Yuan
A26: Hisense Group Holdings Co., Ltd. | B26: 47115559 | C26: IPO2026-03 Project Voyage_CN | D26: Order47115559- 260729002 | E26: 47115559- EDC260729001 | F26: susan.jr.wang,Qun.Hao,Mike.HB.Wang | G26: 46507 | H26: 789.8 | I26: 361.7 | J26: 158 | K26: 203.7 | M26: 海信 | N26: 46307 | O26: 46325 | P26: 46419 | Q26: 46476 | R26: Marsh | S26: Vivi | T26: Luna | U26: Rainbow | V26: Yuan
A27: FORTUNE & ROYAL ASSET MANAGEMENT CORPORATION LIMITED | B27: 47128046 | C27: AUD2026-12 FR Funds | D27: Order47128046- 260501004 | E27: 47128046- EDC260504001 | F27: Hannah.YH.Yu | G27: 46473 | H27: 154.87 | I27: 154.87 | J27: 46.461 | K27: 108.409 | M27: 公募 | P27: 46377 | Q27: 46447 | R27: Marsh | S27: Yuan | T27: Rainbow | U27: InternA | V27: InternB
A28: CMB International Leasing Management Limited | B28: 47133720 | C28: AUD2026-12 CMBILM | D28: Order47133720- 260504003 | E28: 47133720- EDC260504003 | F28: Candy-JX.Wu | G28: 46532 | H28: 411.05 | I28: 411.05 | L28: 411.05 | M28: 招银 | N28: 46371 | O28: 46379 | P28: 46467 | Q28: 46507 | R28: Marsh | S28: Vivi | T28: yuan | U28: Rainbow
A29: Jamesonite Gem (HK) Holdings Limited | B29: 47136348 | C29: AUD2026-12 Warburg Pincus HK SPV JZ | D29: Order47136348- 260504004 | E29: 47136348- EDC260504001 | F29: Eric C Chen | G29: 46550 | H29: 308.61 | I29: 308.61 | L29: 308.61 | M29: PE | P29: 46500 | Q29: 46512 | R29: Marsh | S29: Vivi | T29: Luna | U29: Rainbow

Sheet 人员清单
A1: Name | B1: Grade | C1: hours占比 | D1: 优先项目类型
A2: Marsh.Ma@cn.ey.com | B2: manager
A3: Vivi.W.Yang@cn.ey.com | B3: senior
A4: Yuan.Yuan.YY.Chen@cn.ey.com | B4: staff | D4: 公募
A5: Luna.CD.Zhang@cn.ey.com | B5: staff | D5: PE
A6: Rainbow.MG.Xiao@cn.ey.com | B6: staff | D6: 公募
A7: InternA | B7: intern | D7: 公募
A8: InternB | B8: intern | D8: 公募
